megaparse/__init__.py
megaparse/megaparse.py
megaparse/api/__init__.py
megaparse/api/app.py
megaparse/api/exceptions/__init__.py
megaparse/api/exceptions/megaparse_exceptions.py
megaparse/api/models/__init__.py
megaparse/api/models/base.py
megaparse/configs/auto.py
megaparse/examples/parse_file.py
megaparse/examples/parsing_process.py
megaparse/exceptions/base.py
megaparse/formatter/base.py
megaparse/formatter/structured_formatter/__init__.py
megaparse/formatter/structured_formatter/custom_structured_formatter.py
megaparse/formatter/table_formatter/__init__.py
megaparse/formatter/table_formatter/llm_table_formatter.py
megaparse/formatter/table_formatter/vision_table_formatter.py
megaparse/models/document.py
megaparse/models/page.py
megaparse/parser/__init__.py
megaparse/parser/base.py
megaparse/parser/builder.py
megaparse/parser/doctr_parser.py
megaparse/parser/entity.py
megaparse/parser/llama.py
megaparse/parser/megaparse_vision.py
megaparse/parser/unstructured_parser.py
megaparse/predictor/models/base.py
megaparse/utils/strategy.py
megaparse-0.0.53.dist-info/METADATA
megaparse-0.0.53.dist-info/WHEEL
megaparse-0.0.53.dist-info/RECORD
