Metadata-Version: 2.3
Name: megaparse
Version: 0.0.53
Author-email: Stan Girard <stan@quivr.app>, Chloé Daems <chloe@quivr.app>, Amine Dirhoussi <amine@quivr.app>, Jacopo Chevallard <jacopo@quivr.app>
Requires-Python: >=3.11
Requires-Dist: backoff>=2.2.1
Requires-Dist: langchain-anthropic>=0.1.23
Requires-Dist: langchain-community<0.4,>=0.3
Requires-Dist: langchain-core<0.4,>=0.3
Requires-Dist: langchain-openai>=0.1.21
Requires-Dist: langchain<0.4,>=0.3
Requires-Dist: llama-parse>=0.4.0
Requires-Dist: megaparse-sdk
Requires-Dist: numpy<=2.0.0
Requires-Dist: onnxruntime-gpu==1.20.0; platform_machine == 'x86_64'
Requires-Dist: onnxruntime==1.20.0; platform_machine == 'x86_64'
Requires-Dist: onnxtr[cpu]>=0.6.0; platform_machine != 'x86_64'
Requires-Dist: onnxtr[gpu-headless]>=0.6.0; platform_machine == 'x86_64'
Requires-Dist: pdfplumber>=0.11.0
Requires-Dist: playwright>=1.47.0
Requires-Dist: psutil>=6.1.0
Requires-Dist: pycryptodome>=3.21.0
Requires-Dist: pydantic-settings>=2.6.1
Requires-Dist: pypdf>=5.0.1
Requires-Dist: pypdfium2>=4.30.0
Requires-Dist: python-magic>=0.4.27
Requires-Dist: unstructured[all-docs]==0.15.0
Provides-Extra: api
Requires-Dist: fastapi>=0.115.2; extra == 'api'
Requires-Dist: pydantic-settings>=2.6.1; extra == 'api'
Requires-Dist: python-dotenv>=1.0.0; extra == 'api'
Requires-Dist: ratelimit>=2.2.1; extra == 'api'
Requires-Dist: uvicorn>=0.32.0; extra == 'api'
Requires-Dist: uvloop>=0.18.0; extra == 'api'
